gqrx_client/__init__.py
gqrx_client/__version__.py
gqrx_client/client.py
gqrx_client/transport/__init__.py
gqrx_client/transport/tcp.py
gqrx_client/transport/transport.py
gqrx_client-0.0.1a7.dist-info/METADATA
gqrx_client-0.0.1a7.dist-info/WHEEL
gqrx_client-0.0.1a7.dist-info/licenses/LICENSE
gqrx_client-0.0.1a7.dist-info/RECORD
