Metadata-Version: 2.1
Name: gqrx-client
Version: 0.0.1a7
Summary: A Gqrx Client Library
Project-URL: Homepage, https://github.com/dkerr-dev/python-gqrx-client/
Project-URL: Source, https://github.com/dkerr-dev/python-gqrx-client/
Project-URL: Documentation, https://dkerr-dev.github.io/python-gqrx-client/
Author-email: Daniel Kerr <dkerr.contact@gmail.com>
License-File: LICENSE
Classifier: Programming Language :: Python :: 3
Requires-Python: >=3.10
